<?xml version="1.0" encoding="UTF-8"?>
<?latexml class="beamer"?>
<?latexml RelaxNGSchema="LaTeXML"?>
<document xmlns="http://dlmf.nist.gov/LaTeXML">
  <resource src="LaTeXML.css" type="text/css"/>
  <frame xml:id="frame1">
    <slide overlay="1" xml:id="frame1.slide1">
      <title class="ltx_frame_title">Title</title>
      <subtitle class="ltx_frame_subtitle">Subtitle</subtitle>
      <para xml:id="frame1.slide1.p1">
        <p>Slide 1</p>
      </para>
    </slide>
    <slide overlay="2" xml:id="frame1.slide2">
      <title class="ltx_frame_title">Title</title>
      <subtitle class="ltx_frame_subtitle">Subtitle</subtitle>
      <para xml:id="frame1.slide2.p1">
        <p>Slide 2</p>
      </para>
    </slide>
  </frame>
  <frame xml:id="frame2">
    <slide overlay="1" xml:id="frame2.slide1">
      <title class="ltx_frame_title">Title</title>
      <title class="ltx_frame_shorttitle">Short Title</title>
      <para xml:id="frame2.slide1.p1">
        <p>Slide 1</p>
      </para>
    </slide>
    <slide overlay="2" xml:id="frame2.slide2">
      <title class="ltx_frame_title">Title</title>
      <title class="ltx_frame_shorttitle">Short Title</title>
      <para xml:id="frame2.slide2.p1">
        <p>Slide 2</p>
      </para>
    </slide>
  </frame>
  <frame xml:id="frame3">
    <slide overlay="1" xml:id="frame3.slide1">
      <title class="ltx_frame_title">Title</title>
      <subtitle class="ltx_frame_subtitle">Subtitle</subtitle>
      <para xml:id="frame3.slide1.p1">
        <p>Slide 1</p>
      </para>
    </slide>
    <slide overlay="2" xml:id="frame3.slide2">
      <title class="ltx_frame_title">Title</title>
      <subtitle class="ltx_frame_subtitle">Subtitle</subtitle>
      <para xml:id="frame3.slide2.p1">
        <p>Slide 2</p>
      </para>
    </slide>
  </frame>
  <frame xml:id="frame4">
    <slide overlay="1" xml:id="frame4.slide1">
      <title class="ltx_frame_title">Title</title>
      <subtitle class="ltx_frame_subtitle">Subtitle</subtitle>
      <para xml:id="frame4.slide1.p1">
        <p>Slide 1</p>
      </para>
    </slide>
    <slide overlay="2" xml:id="frame4.slide2">
      <title class="ltx_frame_title">Title</title>
      <subtitle class="ltx_frame_subtitle">Subtitle</subtitle>
      <para xml:id="frame4.slide2.p1">
        <p>Slide 2</p>
      </para>
    </slide>
  </frame>
  <frame xml:id="frame5">
    <slide overlay="1" xml:id="frame5.slide1">
      <para xml:id="frame5.slide1.p1">
        <p>Slide 1</p>
      </para>
    </slide>
    <slide overlay="2" xml:id="frame5.slide2">
      <title class="ltx_frame_title">Title</title>
      <para xml:id="frame5.slide2.p1">
        <p>Slide 2</p>
      </para>
    </slide>
  </frame>
  <frame xml:id="frame6">
    <slide overlay="1" xml:id="frame6.slide1">
      <title class="ltx_frame_title">Title Default</title>
      <para xml:id="frame6.slide1.p1">
        <p>Slide 1</p>
      </para>
    </slide>
    <slide overlay="2" xml:id="frame6.slide2">
      <title class="ltx_frame_title">Second Title</title>
      <para xml:id="frame6.slide2.p1">
        <p>Slide 2</p>
      </para>
    </slide>
  </frame>
  <frame xml:id="frame7">
    <slide overlay="1" xml:id="frame7.slide1">
      <title class="ltx_frame_title">Title Default</title>
      <para xml:id="frame7.slide1.p1">
        <p>Slide 1</p>
      </para>
    </slide>
    <slide overlay="2" xml:id="frame7.slide2">
      <title class="ltx_frame_title">Second Title</title>
      <para xml:id="frame7.slide2.p1">
        <p>Slide 2</p>
      </para>
    </slide>
  </frame>
  <frame xml:id="frame8">
    <slide overlay="1" xml:id="frame8.slide1">
      <title class="ltx_frame_title">Title</title>
      <para xml:id="frame8.slide1.p1">
        <p>Slide 1</p>
      </para>
    </slide>
    <slide overlay="2" xml:id="frame8.slide2">
      <title class="ltx_frame_title">Title</title>
      <subtitle class="ltx_frame_subtitle">Subtitle</subtitle>
      <para xml:id="frame8.slide2.p1">
        <p>Slide 2</p>
      </para>
    </slide>
  </frame>
  <frame xml:id="frame9">
    <slide overlay="1" xml:id="frame9.slide1">
      <title class="ltx_frame_title">Title</title>
      <subtitle class="ltx_frame_subtitle">Subtitle</subtitle>
      <para xml:id="frame9.slide1.p1">
        <p>Slide 1</p>
      </para>
    </slide>
    <slide overlay="2" xml:id="frame9.slide2">
      <title class="ltx_frame_title">Title</title>
      <subtitle class="ltx_frame_subtitle">Second Subtitle</subtitle>
      <para xml:id="frame9.slide2.p1">
        <p>Slide 2</p>
      </para>
    </slide>
  </frame>
  <frame xml:id="frame10">
    <slide overlay="1" xml:id="frame10.slide1">
      <title class="ltx_frame_title">Title</title>
      <subtitle class="ltx_frame_subtitle">Subtitle Default</subtitle>
      <para xml:id="frame10.slide1.p1">
        <p>Slide 1</p>
      </para>
    </slide>
    <slide overlay="2" xml:id="frame10.slide2">
      <title class="ltx_frame_title">Title</title>
      <subtitle class="ltx_frame_subtitle">Second Subtitle</subtitle>
      <para xml:id="frame10.slide2.p1">
        <p>Slide 2</p>
      </para>
    </slide>
  </frame>
</document>
