<?xml version="1.0" encoding="UTF-8"?>
<?latexml class="article"?>
<?latexml package="color"?>
<?latexml package="amsthm"?>
<?latexml RelaxNGSchema="LaTeXML"?>
<document xmlns="http://dlmf.nist.gov/LaTeXML" xmlns:m="http://www.w3.org/1998/Math/MathML" xml:id="Document">
  <resource src="LaTeXML.css" type="text/css"/>
  <resource src="ltx-article.css" type="text/css"/>
  <para xml:id="p1" fragid="p1">
    <p>Preamble file loaded</p>
  </para>
  <para xml:id="p2" fragid="p2">
    <p>Here is a sample fragment:</p>
  </para>
  <para xml:id="p3" fragid="p3">
    <p><Math mode="inline" xml:id="p3.m1" tex="1+2=3" text="1 + 2 = 3" fragid="p3.m1"><m:math alttext="1+2=3" display="inline"><m:semantics><m:mrow xml:id="p3.m1.7" xref="p3.m1.7.cmml"><m:mrow xml:id="p3.m1.4" xref="p3.m1.4.cmml"><m:mn xml:id="p3.m1.1" xref="p3.m1.1.cmml">1</m:mn><m:mo xml:id="p3.m1.2" xref="p3.m1.2.cmml">+</m:mo><m:mn xml:id="p3.m1.3" xref="p3.m1.3.cmml">2</m:mn></m:mrow><m:mo xml:id="p3.m1.5" xref="p3.m1.5.cmml">=</m:mo><m:mn xml:id="p3.m1.6" xref="p3.m1.6.cmml">3</m:mn></m:mrow><m:annotation-xml encoding="MathML-Content"><m:apply xml:id="p3.m1.7.cmml" xref="p3.m1.7"><m:eq xml:id="p3.m1.5.cmml" xref="p3.m1.5"/><m:apply xml:id="p3.m1.4.cmml" xref="p3.m1.4"><m:plus xml:id="p3.m1.2.cmml" xref="p3.m1.2"/><m:cn type="integer" xml:id="p3.m1.1.cmml" xref="p3.m1.1">1</m:cn><m:cn type="integer" xml:id="p3.m1.3.cmml" xref="p3.m1.3">2</m:cn></m:apply><m:cn type="integer" xml:id="p3.m1.6.cmml" xref="p3.m1.6">3</m:cn></m:apply></m:annotation-xml><m:annotation-xml encoding="application/x-latexml"><XMath><XMApp xml:id="p3.m1.7.xm" fragid="p3.m1.7.xm"><XMTok meaning="equals" role="RELOP" xml:id="p3.m1.5.xm" fragid="p3.m1.5.xm">=</XMTok><XMApp xml:id="p3.m1.4.xm" fragid="p3.m1.4.xm"><XMTok meaning="plus" role="ADDOP" xml:id="p3.m1.2.xm" fragid="p3.m1.2.xm">+</XMTok><XMTok meaning="1" role="NUMBER" xml:id="p3.m1.1.xm" fragid="p3.m1.1.xm">1</XMTok><XMTok meaning="2" role="NUMBER" xml:id="p3.m1.3.xm" fragid="p3.m1.3.xm">2</XMTok></XMApp><XMTok meaning="3" role="NUMBER" xml:id="p3.m1.6.xm" fragid="p3.m1.6.xm">3</XMTok></XMApp></XMath></m:annotation-xml><m:annotation encoding="application/x-tex">1+2=3</m:annotation></m:semantics></m:math></Math></p>
  </para>
  <para xml:id="p4" fragid="p4">
    <p>Postamble file loaded.</p>
  </para>
</document>
